{
  "routes": [
    {
      "method": "GET",
      "path": "/specialties",
      "handler": "specialtie.find",
      "config": {
        "policies": []
      }
    },
    {
      "method": "GET",
      "path": "/specialties/count",
      "handler": "specialtie.count",
      "config": {
        "policies": []
      }
    },
    {
      "method": "GET",
      "path": "/specialties/:id",
      "handler": "specialtie.findOne",
      "config": {
        "policies": []
      }
    },
    {
      "method": "POST",
      "path": "/specialties",
      "handler": "specialtie.create",
      "config": {
        "policies": []
      }
    },
    {
      "method": "PUT",
      "path": "/specialties/:id",
      "handler": "specialtie.update",
      "config": {
        "policies": []
      }
    },
    {
      "method": "DELETE",
      "path": "/specialties/:id",
      "handler": "specialtie.delete",
      "config": {
        "policies": []
      }
    }
  ]
}
